Tests/__init__.py
Tests/tests.py
file/__init__.py
file/calculator.py
TACalculator_v3-0.4.dist-info/LICENSE
TACalculator_v3-0.4.dist-info/METADATA
TACalculator_v3-0.4.dist-info/WHEEL
TACalculator_v3-0.4.dist-info/top_level.txt
TACalculator_v3-0.4.dist-info/RECORD
