Metadata-Version: 2.1
Name: TACalculator-v3
Version: 0.4
Summary: Simple calculator, performing basic functions
Author: Tauras Aleksandravicius
Author-email: tauras.al@gmail.com
License: UNKNOWN
Platform: UNKNOWN
Classifier: Programming Language :: Python :: 3
Classifier: Operating System :: OS Independent
License-File: LICENSE
